LICENSE
README.md
setup.py
pyproc/__init__.py
pyproc/exceptions.py
pyproc/lpse.py
pyproc/utils.py
pyproc.egg-info/PKG-INFO
pyproc.egg-info/SOURCES.txt
pyproc.egg-info/dependency_links.txt
pyproc.egg-info/entry_points.txt
pyproc.egg-info/requires.txt
pyproc.egg-info/top_level.txt
pyproc.egg-info/zip-safe
scripts/__init__.py
scripts/downloader.py
scripts/text.py
tests/test_downloader.py
tests/test_lpse.py