Metadata-Version: 2.1
Name: pyproc
Version: 0.1.13
Summary: Python SPSEv4 wrapper
Home-page: https://gitlab.com/wakataw/pyproc
Author: Agung Pratama
Author-email: agungpratama1001@gmail.com
License: MIT
Project-URL: Bug Reports, https://gitlab.com/wakataw/pyproc/issues
Project-URL: Source, https://gitlab.com/wakataw/pyproc
Keywords: api,spse,lpse,pengadaan,procurement,lkpp,lelang,tender
Classifier: Development Status :: 4 - Beta
Classifier: Intended Audience :: Developers
Classifier: Topic :: Internet :: WWW/HTTP :: Dynamic Content :: CGI Tools/Libraries
Classifier: Topic :: Software Development :: Libraries :: Python Modules
Classifier: Topic :: Utilities
Classifier: Natural Language :: English
Classifier: Natural Language :: Indonesian
Classifier: Operating System :: OS Independent
Classifier: Programming Language :: Python :: 3.7
Classifier: License :: OSI Approved :: MIT License
Requires-Python: >=3.7
License-File: LICENSE
